Metadata-Version: 2.1
Name: mandoline-py
Version: 0.8.3
Summary: An STL to GCode slicer for 3D printing, using the clipper libraries.
Home-page: https://github.com/Saatvik-nbil/dhee_sitepackage.git
Author: Revar Desmera
Author-email: revarbat@gmail.com
License: MIT License
Download-URL: https://github.com/Saatvik-nbil/dhee_sitepackage/archive/refs/heads/main.zip
Keywords: stl gcode slicer 3dprinting
Platform: UNKNOWN
Classifier: Development Status :: 3 - Alpha
Classifier: Environment :: Console
Classifier: Environment :: Console
Classifier: Intended Audience :: End Users/Desktop
Classifier: Intended Audience :: Manufacturing
Classifier: Intended Audience :: Science/Research
Classifier: License :: OSI Approved :: MIT License
Classifier: Natural Language :: English
Classifier: Operating System :: MacOS :: MacOS X
Classifier: Operating System :: Microsoft :: Windows
Classifier: Operating System :: POSIX
Classifier: Programming Language :: Python :: 2
Classifier: Programming Language :: Python :: 3
Classifier: Topic :: Multimedia :: Graphics :: 3D Modeling
Requires-Python: >=3.10
License-File: LICENSE
Requires-Dist: setuptools
Requires-Dist: six >=1.10.0
Requires-Dist: pyquaternion >=0.9.5
Requires-Dist: pyclipper >=1.1.0
Requires-Dist: appdirs >=1.4.3
Provides-Extra: dev
Requires-Dist: pytest >=7.0 ; extra == 'dev'
Requires-Dist: twine >=4.0.2 ; extra == 'dev'
